pyDtwSat/__init__.py
pyDtwSat/dtw.py
pyDtwSat/models.py
pyDtwSat/timeseries.py
pyDtwSat-0.1.2.dist-info/LICENSE
pyDtwSat-0.1.2.dist-info/METADATA
pyDtwSat-0.1.2.dist-info/WHEEL
pyDtwSat-0.1.2.dist-info/top_level.txt
pyDtwSat-0.1.2.dist-info/RECORD
