Metadata-Version: 2.1
Name: pyDtwSat
Version: 0.1.2
Summary: Python adaptation of R lirary dtwSat
Home-page: https://github.com/Kira1690/pyDtwSat.git
Author: Vishal D Dafada
Author-email: dafadavishal6@gmail.com
License: Apache 2.0
Keywords: Satellite image Analysis
Platform: UNKNOWN
Requires-Python: >=3.8, <4
License-File: LICENSE
Requires-Dist: scipy
Requires-Dist: matplotlib
Requires-Dist: pandas
Requires-Dist: sklern
